hypercorn/__init__.py
hypercorn/__main__.py
hypercorn/app_wrappers.py
hypercorn/asyncio/__init__.py
hypercorn/asyncio/lifespan.py
hypercorn/asyncio/run.py
hypercorn/asyncio/statsd.py
hypercorn/asyncio/task_group.py
hypercorn/asyncio/tcp_server.py
hypercorn/asyncio/udp_server.py
hypercorn/asyncio/worker_context.py
hypercorn/config.py
hypercorn/events.py
hypercorn/logging.py
hypercorn/middleware/__init__.py
hypercorn/middleware/dispatcher.py
hypercorn/middleware/http_to_https.py
hypercorn/middleware/proxy_fix.py
hypercorn/middleware/wsgi.py
hypercorn/protocol/__init__.py
hypercorn/protocol/events.py
hypercorn/protocol/h11.py
hypercorn/protocol/h2.py
hypercorn/protocol/h3.py
hypercorn/protocol/http_stream.py
hypercorn/protocol/quic.py
hypercorn/protocol/ws_stream.py
hypercorn/py.typed
hypercorn/run.py
hypercorn/statsd.py
hypercorn/trio/__init__.py
hypercorn/trio/lifespan.py
hypercorn/trio/run.py
hypercorn/trio/statsd.py
hypercorn/trio/task_group.py
hypercorn/trio/tcp_server.py
hypercorn/trio/udp_server.py
hypercorn/trio/worker_context.py
hypercorn/typing.py
hypercorn/utils.py
hypercorn-0.17.2.dist-info/LICENSE
hypercorn-0.17.2.dist-info/METADATA
hypercorn-0.17.2.dist-info/WHEEL
hypercorn-0.17.2.dist-info/entry_points.txt
hypercorn-0.17.2.dist-info/RECORD
