Metadata-Version: 2.1
Name: Hypercorn
Version: 0.17.2
Summary: A ASGI Server based on Hyper libraries and inspired by Gunicorn
Home-page: https://github.com/pgjones/hypercorn/
License: MIT
Author: pgjones
Author-email: philip.graham.jones@googlemail.com
Requires-Python: >=3.8
Classifier: Development Status :: 4 - Beta
Classifier: Environment :: Web Environment
Classifier: Intended Audience :: Developers
Classifier: License :: OSI Approved :: MIT License
Classifier: Operating System :: OS Independent
Classifier: Programming Language :: Python
Classifier: Programming Language :: Python :: 3
Classifier: Programming Language :: Python :: 3.8
Classifier: Programming Language :: Python :: 3.9
Classifier: Programming Language :: Python :: 3.10
Classifier: Programming Language :: Python :: 3.11
Classifier: Programming Language :: Python :: 3.12
Classifier: Topic :: Internet :: WWW/HTTP :: Dynamic Content
Classifier: Topic :: Software Development :: Libraries :: Python Modules
Provides-Extra: docs
Provides-Extra: h3
Provides-Extra: trio
Provides-Extra: uvloop
Requires-Dist: aioquic (>=0.9.0,<1.0) ; extra == "h3"
Requires-Dist: exceptiongroup (>=1.1.0) ; python_version < "3.11"
Requires-Dist: h11
Requires-Dist: h2 (>=3.1.0)
Requires-Dist: priority
Requires-Dist: pydata_sphinx_theme ; extra == "docs"
Requires-Dist: sphinxcontrib_mermaid ; extra == "docs"
Requires-Dist: taskgroup ; python_version < "3.11"
Requires-Dist: tomli ; python_version < "3.11"
Requires-Dist: trio (>=0.22.0) ; extra == "trio"
Requires-Dist: typing_extensions ; python_version < "3.11"
Requires-Dist: uvloop ; (platform_system != "Windows") and (extra == "uvloop")
Requires-Dist: wsproto (>=0.14.0)
Project-URL: Documentation, https://hypercorn.readthedocs.io
Project-URL: Repository, https://github.com/pgjones/hypercorn/
